hcml/Hachi_filter.py
hcml/__init__.py
hcml/meaningless.py
hcml/test_for_ml.py
hcml-0.0.1.dist-info/DESCRIPTION.rst
hcml-0.0.1.dist-info/METADATA
hcml-0.0.1.dist-info/RECORD
hcml-0.0.1.dist-info/WHEEL
hcml-0.0.1.dist-info/metadata.json
hcml-0.0.1.dist-info/top_level.txt
